ScalaChuxueZhinan/README.md
ScalaChuxueZhinan/__init__.py
ScalaChuxueZhinan/__main__.py
ScalaChuxueZhinan/file.epub
ScalaChuxueZhinan/index.html
ScalaChuxueZhinan/css/__init__.py
ScalaChuxueZhinan/css/annotations.css
ScalaChuxueZhinan/css/main.css
ScalaChuxueZhinan/css/normalize.css
ScalaChuxueZhinan/css/popup.css
ScalaChuxueZhinan/font/__init__.py
ScalaChuxueZhinan/font/fontello.eot
ScalaChuxueZhinan/font/fontello.svg
ScalaChuxueZhinan/font/fontello.ttf
ScalaChuxueZhinan/font/fontello.woff
ScalaChuxueZhinan/img/__init__.py
ScalaChuxueZhinan/img/annotator-glyph-sprite.png
ScalaChuxueZhinan/img/annotator-icon-sprite.png
ScalaChuxueZhinan/img/apple-touch-icon.png
ScalaChuxueZhinan/img/cancelfullscreen.png
ScalaChuxueZhinan/img/close.png
ScalaChuxueZhinan/img/fullscreen.png
ScalaChuxueZhinan/img/loader.gif
ScalaChuxueZhinan/img/menu-icon.png
ScalaChuxueZhinan/img/save.png
ScalaChuxueZhinan/img/saved.png
ScalaChuxueZhinan/img/settings-s.png
ScalaChuxueZhinan/img/settings.png
ScalaChuxueZhinan/img/star.png
ScalaChuxueZhinan/js/__init__.py
ScalaChuxueZhinan/js/epub.js
ScalaChuxueZhinan/js/epub.min.js
ScalaChuxueZhinan/js/epub.min.map
ScalaChuxueZhinan/js/hooks.min.js
ScalaChuxueZhinan/js/hooks.min.map
ScalaChuxueZhinan/js/reader.js
ScalaChuxueZhinan/js/reader.js.map
ScalaChuxueZhinan/js/reader.min.js
ScalaChuxueZhinan/js/reader.min.map
ScalaChuxueZhinan/js/hooks/__init__.py
ScalaChuxueZhinan/js/hooks/extensions/__init__.py
ScalaChuxueZhinan/js/hooks/extensions/highlight.js
ScalaChuxueZhinan/js/libs/__init__.py
ScalaChuxueZhinan/js/libs/jquery.min.js
ScalaChuxueZhinan/js/libs/localforage.min.js
ScalaChuxueZhinan/js/libs/screenfull.js
ScalaChuxueZhinan/js/libs/screenfull.min.js
ScalaChuxueZhinan/js/libs/zip.min.js
ScalaChuxueZhinan/js/plugins/__init__.py
ScalaChuxueZhinan/js/plugins/hypothesis.js
ScalaChuxueZhinan/js/plugins/search.js
scala_chuxue_zhinan-2024.3.3.0.dist-info/METADATA
scala_chuxue_zhinan-2024.3.3.0.dist-info/WHEEL
scala_chuxue_zhinan-2024.3.3.0.dist-info/entry_points.txt
scala_chuxue_zhinan-2024.3.3.0.dist-info/top_level.txt
scala_chuxue_zhinan-2024.3.3.0.dist-info/RECORD
